crcarla/__init__.py
crcarla/carla_interface.py
crcarla/controller/__init__.py
crcarla/controller/commonroad_planner.py
crcarla/controller/controller.py
crcarla/controller/keyboard_controller.py
crcarla/controller/pedestrian_controller.py
crcarla/controller/reactive_planner.py
crcarla/controller/steering_wheel.py
crcarla/controller/vehicle_controller.py
crcarla/helper/__init__.py
crcarla/helper/config.py
crcarla/helper/traffic_generation.py
crcarla/helper/utils.py
crcarla/helper/vehicle_dict.py
crcarla/objects/__init__.py
crcarla/objects/actor.py
crcarla/objects/pedestrian.py
crcarla/objects/traffic_light.py
crcarla/objects/vehicle.py
crcarla/visualization/__init__.py
crcarla/visualization/canvas/__init__.py
crcarla/visualization/canvas/canvas_controller.py
crcarla/visualization/canvas/ui_elements/__init__.py
crcarla/visualization/canvas/ui_elements/fading_text.py
crcarla/visualization/canvas/ui_elements/help_text.py
crcarla/visualization/canvas/ui_elements/text.py
crcarla/visualization/common.py
crcarla/visualization/sensors/__init__.py
crcarla/visualization/sensors/sensor_controller.py
crcarla/visualization/sensors/sensor_types/__init__.py
crcarla/visualization/sensors/sensor_types/camera_sensor.py
crcarla/visualization/sensors/sensor_types/collision_sensor.py
crcarla/visualization/sensors/sensor_types/gnss_sensor.py
crcarla/visualization/sensors/sensor_types/imu_sensor.py
crcarla/visualization/sensors/sensor_types/lane_invasion_sensor.py
crcarla/visualization/visualization2D.py
crcarla/visualization/visualization3D.py
crcarla/visualization/visualization_base.py
crcarla/visualization/visualization_tools/__init__.py
crcarla/visualization/visualization_tools/tools/__init__.py
crcarla/visualization/visualization_tools/tools/bounding_box_tool.py
crcarla/visualization/visualization_tools/tools/line_to_vehicle.py
crcarla/visualization/visualization_tools/tools/polygon_tool.py
crcarla/visualization/visualization_tools/tools/text.py
commonroad_carla_interface-1.0.0.dist-info/LICENSE.txt
commonroad_carla_interface-1.0.0.dist-info/METADATA
commonroad_carla_interface-1.0.0.dist-info/WHEEL
commonroad_carla_interface-1.0.0.dist-info/RECORD
