Metadata-Version: 2.1
Name: commonroad-carla-interface
Version: 1.0.0
Summary: Interface between CommonRoad and the traffic simulator CARLA.
Home-page: https://commonroad.in.tum.de
License: GPL-3.0
Keywords: autonomous,automated,vehicles,driving,motion,planning,simulation
Author: Cyber-Physical Systems Group, Technical University of Munich
Author-email: commonroad@lists.lrz.de
Requires-Python: >=3.9,<3.11
Classifier: License :: OSI Approved :: GNU General Public License v3 (GPLv3)
Classifier: Operating System :: POSIX :: Linux
Classifier: Programming Language :: Python :: 3
Classifier: Programming Language :: Python :: 3.9
Classifier: Programming Language :: Python :: 3.10
Requires-Dist: carla (==0.9.15)
Requires-Dist: commonroad-drivability-checker (>=2024.1)
Requires-Dist: commonroad-io (>=2024.2,<=2024.3)
Requires-Dist: commonroad-prediction (>=0.1.1,<0.2.0)
Requires-Dist: commonroad-reactive-planner (==2024.1)
Requires-Dist: commonroad-route-planner (>=2024.2.0,<2025.0.0)
Requires-Dist: commonroad-scenario-designer (==0.8.4)
Requires-Dist: commonroad_vehicle_models (>=3.0.2)
Requires-Dist: matplotlib (>=2.2.2,<3.9.0)
Requires-Dist: numpy (>=1.26.1,<2.0.0)
Requires-Dist: omegaconf (>=2.1.2)
Requires-Dist: psutil (>=5.9.4,<6.0.0)
Requires-Dist: pygame (>=2.1.2)
Requires-Dist: scipy (>=1.11.3,<2.0.0)
Project-URL: Documentation, https://cps.pages.gitlab.lrz.de/commonroad/commonroad-carla-interface/
Project-URL: Forum, https://github.com/CommonRoad/commonroad-carla-interface/discussions
Project-URL: Source, https://github.com/CommonRoad/commonroad-carla-interface
